odoo/addons/barcodes_generator_partner/README.rst
odoo/addons/barcodes_generator_partner/__init__.py
odoo/addons/barcodes_generator_partner/__manifest__.py
odoo/addons/barcodes_generator_partner/demo/barcode_rule.xml
odoo/addons/barcodes_generator_partner/demo/function.xml
odoo/addons/barcodes_generator_partner/demo/ir_sequence.xml
odoo/addons/barcodes_generator_partner/demo/res_partner.xml
odoo/addons/barcodes_generator_partner/i18n/barcodes_generator_partner.pot
odoo/addons/barcodes_generator_partner/i18n/es.po
odoo/addons/barcodes_generator_partner/i18n/es_ES.po
odoo/addons/barcodes_generator_partner/i18n/fr.po
odoo/addons/barcodes_generator_partner/i18n/hr.po
odoo/addons/barcodes_generator_partner/i18n/nl_NL.po
odoo/addons/barcodes_generator_partner/models/__init__.py
odoo/addons/barcodes_generator_partner/models/barcode_rule.py
odoo/addons/barcodes_generator_partner/models/res_partner.py
odoo/addons/barcodes_generator_partner/static/description/icon.png
odoo/addons/barcodes_generator_partner/static/description/res_partner_sequence_generation.png
odoo/addons/barcodes_generator_partner/tests/__init__.py
odoo/addons/barcodes_generator_partner/tests/test_barcodes_generator_partner.py
odoo/addons/barcodes_generator_partner/views/view_res_partner.xml
odoo11_addon_barcodes_generator_partner-11.0.1.0.0.99.dev1.dist-info/METADATA
odoo11_addon_barcodes_generator_partner-11.0.1.0.0.99.dev1.dist-info/RECORD
odoo11_addon_barcodes_generator_partner-11.0.1.0.0.99.dev1.dist-info/WHEEL
odoo11_addon_barcodes_generator_partner-11.0.1.0.0.99.dev1.dist-info/top_level.txt
